{
  "affiliations": [
    "Red Hair Pirates"
  ],
  "age": 50,
  "birthday": "November 9th",
  "bounty": 0,
  "cn": {
    "affiliations": [
      "红发海贼团"
    ],
    "debut_arc": "冒险的黎明",
    "haki": [
      "武装色"
    ],
    "name": "本·贝克曼",
    "origin": "北海"
  },
  "debut_arc": "Romance Dawn",
  "debut_chapter": 1,
  "haki": [
    "armament"
  ],
  "height": 206,
  "image": "https://static.wikia.nocookie.net/onepiece/images/1/12/Benn_Beckman_Anime_Infobox.png/revision/latest/scale-to-width-down/268?cb=20240623091906",
  "japanese_name": "ベン・ベックマン",
  "name": "Benn Beckman",
  "occupations": [
    "Pirate",
    "First Mate"
  ],
  "origin": "North Blue",
  "status": "Alive"
}