{
  "affiliations": [
    "Cross Guild",
    "Seven Warlords of the Sea (former)"
  ],
  "age": 43,
  "birthday": "March 9th",
  "bounty": 3590000000,
  "cn": {
    "affiliations": [
      "十字海贼团",
      "七武海"
    ],
    "debut_arc": "海上餐厅篇",
    "haki": [
      "武装色",
      "见闻色"
    ],
    "name": "德拉库尔·米霍克",
    "origin": "未知"
  },
  "debut_arc": "Baratie",
  "debut_chapter": 49,
  "haki": [
    "armament",
    "observation"
  ],
  "height": 198,
  "image": "https://static.wikia.nocookie.net/onepiece/images/b/bf/Dracule_Mihawk_Anime_Infobox.png/revision/latest/scale-to-width-down/267?cb=20151222105910",
  "japanese_name": "ジュラキュール・ミホーク",
  "name": "Dracule Mihawk",
  "occupations": [
    "Pirate",
    "Cross Guild Chief Officer",
    "Warlord of the Sea (former)"
  ],
  "origin": "Unknown",
  "residence": [
    "Kuraigana Island (former)",
    "Karai Bari Island"
  ],
  "status": "Alive"
}