{
  "affiliations": [
    "Revolutionary Army (North Army)"
  ],
  "age": 47,
  "birthday": "September 18th",
  "bounty": 400000000,
  "cn": {
    "affiliations": [
      "革命军"
    ],
    "debut_arc": "顶上战争后篇",
    "devil_fruit_name": "煤煤果实",
    "devil_fruit_type": "自然系",
    "haki": [
      "武装色",
      "见闻色"
    ],
    "name": "卡拉苏",
    "origin": "北海"
  },
  "debut_arc": "Post-War",
  "debut_chapter": 593,
  "devil_fruit_name": "Soot-Soot Fruit",
  "devil_fruit_type": "Logia",
  "haki": [
    "armament",
    "observation"
  ],
  "height": 265,
  "image": "https://static.wikia.nocookie.net/onepiece/images/9/9a/Karasu_Anime_Infobox.png/revision/latest/scale-to-width-down/268?cb=20190414113619",
  "japanese_name": "カラス",
  "name": "Karasu",
  "occupations": [
    "North Army Commander of the Revolutionary Army"
  ],
  "origin": "North Blue",
  "residence": [
    "Baltigo (former)",
    "Momoiro Island"
  ],
  "status": "Alive"
}