{
  "affiliations": [
    "Wano Country (Kurozumi Family)"
  ],
  "birthday": "August 19th",
  "bounty": 0,
  "cn": {
    "affiliations": [
      "和之国"
    ],
    "debut_arc": "和之国篇·第二幕",
    "devil_fruit_name": "克隆果实",
    "devil_fruit_type": "超人系",
    "haki": [],
    "name": "黑炭·日暮",
    "origin": "伟大航路"
  },
  "debut_arc": "Wano Country Act 2",
  "debut_chapter": 965,
  "devil_fruit_name": "Clone-Clone Fruit",
  "devil_fruit_type": "Paramecia",
  "haki": [],
  "height": 193,
  "image": "https://static.wikia.nocookie.net/onepiece/images/d/d6/Kurozumi_Higurashi_Anime_Infobox.png/revision/latest/scale-to-width-down/268?cb=20210418042139",
  "japanese_name": "黒炭ひぐらし",
  "name": "Kurozumi Higurashi",
  "origin": "Grand Line",
  "residence": [
    "Wano Country (Flower Capital)"
  ],
  "status": "Deceased"
}