{
  "affiliations": [
    "Riku Family"
  ],
  "age": 60,
  "birthday": "June 27th",
  "bounty": 0,
  "cn": {
    "affiliations": [
      "里库家"
    ],
    "debut_arc": "德雷斯罗萨",
    "haki": [],
    "name": "里库·多尔多三世",
    "origin": "伟大航路"
  },
  "debut_arc": "Dressrosa",
  "debut_chapter": 706,
  "haki": [],
  "height": 261,
  "image": "https://static.wikia.nocookie.net/onepiece/images/4/48/Riku_Doldo_III_Anime_Infobox.png/revision/latest/scale-to-width-down/268?cb=20230114034249",
  "japanese_name": "リク・ドルド3世",
  "name": "Riku Doldo III",
  "occupations": [
    "King",
    "Corrida Colosseum Gladiator (former)"
  ],
  "origin": "Grand Line",
  "residence": [
    "Dressrosa"
  ],
  "status": "Alive"
}