{
  "affiliations": [
    "Red Hair Pirates (former)"
  ],
  "age": 21,
  "birthday": "October 1st",
  "bounty": 0,
  "cn": {
    "affiliations": [
      "红发海贼团"
    ],
    "debut_arc": "和之国篇·第三幕",
    "devil_fruit_name": "唱唱果实",
    "devil_fruit_type": "超人系",
    "haki": [],
    "name": "乌塔",
    "origin": "未知"
  },
  "debut_arc": "Wano Country Act 3",
  "debut_chapter": 1055,
  "devil_fruit_name": "Sing-Sing Fruit",
  "devil_fruit_type": "Paramecia",
  "haki": [],
  "height": 169,
  "image": "https://static.wikia.nocookie.net/onepiece/images/0/06/Uta_Anime_Infobox.png/revision/latest/scale-to-width-down/268?cb=20250818013702",
  "japanese_name": "ウタ",
  "name": "Uta",
  "occupations": [
    "Singer",
    "Musician (former)",
    "Pirate (former)"
  ],
  "origin": "Unknown",
  "residence": [
    "Elegia (former)"
  ],
  "status": "Unknown"
}